MANIFEST.in
README.md
licence.txt
pyped.py
setup.py
Pyped.egg-info/PKG-INFO
Pyped.egg-info/SOURCES.txt
Pyped.egg-info/dependency_links.txt
Pyped.egg-info/entry_points.txt
Pyped.egg-info/requires.txt
Pyped.egg-info/top_level.txt