Metadata-Version: 1.1
Name: Pyped
Version: 1.1
Summary: Command that pipes data from bash to Python, and vice-versa
Home-page: http://github.com/ksamuel/Pyped
Author: Kevin Samuel
Author-email: kevin.samuel@yandex.com
License: GPL2
Keywords: python,pipe
Platform: UNKNOWN
Classifier: Intended Audience :: Developers
Classifier: Programming Language :: Python
Classifier: Operating System :: OS Independent
